webtest_flask_fixture/__init__.py
webtest_flask_fixture/fixture_template/__init__.py
webtest_flask_fixture/test_app_mod/__init__.py
webtest_flask_fixture-0.5.1.dist-info/LICENSE
webtest_flask_fixture-0.5.1.dist-info/METADATA
webtest_flask_fixture-0.5.1.dist-info/WHEEL
webtest_flask_fixture-0.5.1.dist-info/top_level.txt
webtest_flask_fixture-0.5.1.dist-info/RECORD
