Metadata-Version: 2.1
Name: webtest-flask-fixture
Version: 0.5.1
Summary: Provide a pytest fixture of a Webtest app with a local static site via Flask
Home-page: https://github.com/mshafer1/webtest-flask-fixture
Author: mshafer1
License: UNKNOWN
Project-URL: Bug Reports, https://github.com/mshafer1/webtest-flask-fixture/issues
Project-URL: Source, https://github.com/mshafer1/webtest-flask-fixture
Keywords: WebTest Flask PyTest static-sites
Platform: UNKNOWN
Classifier: Development Status :: 1 - Planning
Classifier: Intended Audience :: Developers
Classifier: Topic :: Software Development :: Testing :: Unit
Classifier: License :: OSI Approved :: MIT License
Classifier: Programming Language :: Python :: 3
Classifier: Programming Language :: Python :: 3.5
Classifier: Programming Language :: Python :: 3.6
Classifier: Programming Language :: Python :: 3.7
Requires-Python: >=2.7, !=3.0.*, !=3.1.*, !=3.2.*, !=3.3.*, !=3.4.*, <4
Requires-Dist: pytest
Requires-Dist: webtest
Requires-Dist: flask
Requires-Dist: pytest-mock (>=1.10.4)
Provides-Extra: test
Requires-Dist: pytest-cov ; extra == 'test'
